{
  "axes": [
    {
      "scale": "x",
      "title": "time",
      "type": "x"
    },
    {
      "scale": "y",
      "title": "kwatts",
      "type": "y"
    }
  ],
  "data": [
    {
      "name": "table",
      "values": [
        {
          "col": "prediction",
          "idx": 1621904400000,
          "val": 0.43730807304382324
        },
        {
          "col": "prediction",
          "idx": 1621908000000,
          "val": 0.4635138213634491
        },
        {
          "col": "prediction",
          "idx": 1621911600000,
          "val": 0.4657517671585083
        },
        {
          "col": "prediction",
          "idx": 1621915200000,
          "val": 0.41119587421417236
        },
        {
          "col": "prediction",
          "idx": 1621918800000,
          "val": 0.2943619191646576
        },
        {
          "col": "prediction",
          "idx": 1621922400000,
          "val": 0.1585397571325302
        },
        {
          "col": "prediction",
          "idx": 1621926000000,
          "val": 0.08618862926959991
        },
        {
          "col": "prediction",
          "idx": 1621929600000,
          "val": 0.019583193585276604
        },
        {
          "col": "prediction",
          "idx": 1621933200000,
          "val": 0.0020227159839123487
        },
        {
          "col": "prediction",
          "idx": 1621936800000,
          "val": 0.00014825172547716647
        },
        {
          "col": "prediction",
          "idx": 1621940400000,
          "val": 0.0001687251788098365
        },
        {
          "col": "prediction",
          "idx": 1621944000000,
          "val": 5.222324762144126e-05
        },
        {
          "col": "prediction",
          "idx": 1621947600000,
          "val": 0.0005913206259720027
        },
        {
          "col": "prediction",
          "idx": 1621951200000,
          "val": 0.0016180663369596004
        },
        {
          "col": "prediction",
          "idx": 1621954800000,
          "val": 0.0010126350680366158
        },
        {
          "col": "prediction",
          "idx": 1621958400000,
          "val": 0.0006803409778513014
        },
        {
          "col": "prediction",
          "idx": 1621962000000,
          "val": 0.0013345604529604316
        },
        {
          "col": "prediction",
          "idx": 1621965600000,
          "val": 0.0023482907563447952
        },
        {
          "col": "prediction",
          "idx": 1621969200000,
          "val": 0.0034573276061564684
        },
        {
          "col": "prediction",
          "idx": 1621972800000,
          "val": 0.0051386719569563866
        },
        {
          "col": "prediction",
          "idx": 1621976400000,
          "val": 0.01833093911409378
        },
        {
          "col": "prediction",
          "idx": 1621980000000,
          "val": 0.12639489769935608
        },
        {
          "col": "prediction",
          "idx": 1621983600000,
          "val": 0.256733775138855
        },
        {
          "col": "prediction",
          "idx": 1621987200000,
          "val": 0.38288798928260803
        },
        {
          "col": "prediction",
          "idx": 1621990800000,
          "val": 0.46563538908958435
        }
      ]
    }
  ],
  "height": 200,
  "legends": [],
  "marks": [
    {
      "from": {
        "data": "table",
        "transform": [
          {
            "keys": [
              "data.col"
            ],
            "type": "facet"
          }
        ]
      },
      "marks": [
        {
          "properties": {
            "enter": {
              "stroke": {
                "field": "data.col",
                "scale": "color"
              },
              "strokeWidth": {
                "value": 2
              },
              "x": {
                "field": "data.idx",
                "scale": "x"
              },
              "y": {
                "field": "data.val",
                "scale": "y"
              }
            }
          },
          "type": "line"
        }
      ],
      "type": "group"
    }
  ],
  "padding": "auto",
  "scales": [
    {
      "domain": {
        "data": "table",
        "field": "data.idx"
      },
      "name": "x",
      "range": "width",
      "type": "time"
    },
    {
      "domain": {
        "data": "table",
        "field": "data.val"
      },
      "name": "y",
      "nice": true,
      "range": "height"
    },
    {
      "domain": {
        "data": "table",
        "field": "data.col"
      },
      "name": "color",
      "range": "category20",
      "type": "ordinal"
    }
  ],
  "width": 450
}